client/__init__.py
client/client.py
client/login_ui.py
client/main.py
client/metacls.py
client/register_ui.py
client/common/__init__.py
client/common/settings.py
client/log/__init__.py
client/log/client_log_config.py
moths_client-0.0.2.dist-info/METADATA
moths_client-0.0.2.dist-info/WHEEL
moths_client-0.0.2.dist-info/top_level.txt
moths_client-0.0.2.dist-info/RECORD
