Metadata-Version: 2.1
Name: moths-client
Version: 0.0.2
Summary: messenger_project_client
Home-page: UNKNOWN
Author: Fedor Kleshchev
Author-email: f.kleshev@gmail.com
License: UNKNOWN
Platform: UNKNOWN
Requires-Dist: PyQt5
Requires-Dist: hashlib
